Tarea 1/sumador4.v
/*
Sumador binario sincrónico de 4 bits, con los siguientes modos de funcionamiento:
a) Suma
b) Resta
c) Mantener valor anterior
d) Limpiar el sumador
*/

module sumador4 (   input   CLK,
                    input   ENB,
                    input   RCI,
                    input   [1:0] MODO,
                    input   [3:0] A,
                    input   [3:0] B,
                    output  reg [3:0] Q  = 0,
                    output  reg RCO);

wire [3:0] negB;
assign negB = ~B + 1'b1;


always @(posedge CLK) begin
    if (ENB) begin
        case ({MODO, RCI})
            3'b00x: Q <= Q ;
            3'b010: begin
                        {RCO, Q} <= A + B;
                    end
            3'b011: Q <= A + B + 1'b1;
            3'b10x: begin
                        {RCO, Q} <= A + negB;
                    end
            3'b11x: Q <= 4'b0;
        endcase
    end
end

endmodule

Tarea 1/sumador4_tb.v
`timescale 1ns/1ns
`include "sumador4.v"


module sumador4_tb;

    // Inputs
    reg CLK;
    reg ENB;
    reg [1:0] MODO;
    reg [3:0] A;
    reg [3:0] B;
    reg RCI;

    // Outputs
    wire [3:0] Q;
    wire RCO;

    // Instantiate the design under test
    sumador4 dut (
        .CLK(CLK),
        .ENB(ENB),
        .MODO(MODO),
        .RCI(RCI),
        .A(A),
        .B(B),
        .Q(Q),
        .RCO(RCO)
    );

    // Initialize the inputs
    initial begin
        $dumpfile("sumador4_tb.vcd");
        $dumpvars(0, sumador4_tb);
        CLK = 0;
        ENB = 1;
        MODO = 2'b01;
        RCI = 0;
        A = 4;
        B = 3;

        #10;
        A = 7;
        B = 2;

        #10;
        A = 4'b1111;
        B = 1'b1;

        #10;
        A = 0;
        B = 0;

        #10;
        $finish;
    end

    // Toggle the clock signal
    always #5 CLK = ~CLK;

    
    

endmodule

Tarea 1/sumador4_tb.vcd
$date
	Sun Mar 26 18:30:55 2023
$end
$version
	Icarus Verilog
$end
$timescale
	1ns
$end
$scope module sumador4_tb $end
$var wire 1 ! RCO $end
$var wire 4 " Q [3:0] $end
$var reg 4 # A [3:0] $end
$var reg 4 $ B [3:0] $end
$var reg 1 % CLK $end
$var reg 1 & ENB $end
$var reg 2 ' MODO [1:0] $end
$var reg 1 ( RCI $end
$scope module dut $end
$var wire 4 ) A [3:0] $end
$var wire 4 * B [3:0] $end
$var wire 1 % CLK $end
$var wire 1 & ENB $end
$var wire 2 + MODO [1:0] $end
$var wire 1 ( RCI $end
$var wire 4 , negB [3:0] $end
$var reg 4 - Q [3:0] $end
$var reg 1 ! RCO $end
$upscope $end
$upscope $end
$enddefinitions $end
$comment Show the parameter values. $end
$dumpall
$end
#0
$dumpvars
b0 -
b1101 ,
b1 +
b11 *
b100 )
0(
b1 '
1&
0%
b11 $
b100 #
b0 "
x!
$end
#5
0!
b111 "
b111 -
1%
#10
b1110 ,
0%
b10 $
b10 *
b111 #
b111 )
#15
b1001 "
b1001 -
1%
#20
b1111 ,
0%
b1 $
b1 *
b1111 #
b1111 )
#25
1!
b0 "
b0 -
1%
#30
b0 ,
0%
b0 $
b0 *
b0 #
b0 )
#35
0!
1%
