Tarea 1/sumador4.v
/*
Sumador binario sincrónico de 4 bits, con los siguientes modos de funcionamiento:
a) Suma
b) Resta
c) Mantener valor anterior
d) Limpiar el sumador
*/

module sumador4 (   input   CLK,
                    input   ENB,
                    input   RCI,
                    input   [1:0] MODO,
                    input   [3:0] A,
                    input   [3:0] B,
                    output  reg [3:0] Q,
                    output  reg RCO);

wire [3:0] negB;
assign negB = ~B + 1'b1;


always @(posedge CLK) begin
    if (ENB) begin
        case ({MODO, RCI})
            3'b00x: Q <= Q ;
            3'b010: begin
                        {RCO, Q} <= A + B;
                    end
            3'b011: {RCO, Q} <= A + B + 1'b1;
            3'b100: begin
                        {RCO, Q} <= A + ~B + 1'b1;
                    end
            //3'b101: {RCO, Q} <= A + ~B + 2'b10;
            3'b101: {RCO, Q} <= 5'b11111;
            3'b110: Q <= 4'b0;
        endcase
    end
end

endmodule

Tarea 1/sumador8.v
`include "sumador4.v"

module sumador8 (   input   CLK,
                    input   ENB,
                    input   RCI,
                    input   [1:0] MODO,
                    input   [7:0] A,
                    input   [7:0] B,
                    output  [7:0] Q,
                    output  RCO);

wire C1;
wire [3:0] Q1, Q2;
reg W1; // Preguntar sobre este método de anticipación
reg [3:0] W2, W3;

always @(A or B) begin
    if (MODO == 2'b01) begin
        // Wires para el carreo (del bloque 1 a bloque 2) y para las salidas
        {W1, W2} = A[3:0] + B[3:0];
    end

    if (MODO == 2'b10) begin
        W3 = ~B + 1'b1;
        {W1, W2} = A[3:0] - B[3:0];
    end
end

// Instancias de módulo sumador4
sumador4 bloque1 (.CLK(CLK), .ENB(ENB), .RCI(RCI), .MODO(MODO), .A(A[3:0]), .B(B[3:0]), .Q(Q1), .RCO(C1));
sumador4 bloque2 (.CLK(CLK), .ENB(ENB), .RCI(W1), .MODO(MODO), .A(A[7:4]), .B(B[7:4]), .Q(Q2), .RCO(RCO));

// Se concatenan los resultados de ambos sumadores
assign Q = {Q2, Q1};

endmodule

Tarea_1/sumador8_tb.v
`timescale 1ns/1ns
`include "sumador8.v"


module sumador8_tb;

    // Inputs
    reg CLK;
    reg ENB;
    reg [1:0] MODO;
    reg [7:0] A;
    reg [7:0] B;
    reg RCI;

    // Outputs
    wire [7:0] Q;
    wire RCO;

    // Instantiate the design under test
    sumador8 dut (
        .CLK(CLK),
        .ENB(ENB),
        .MODO(MODO),
        .RCI(RCI),
        .A(A),
        .B(B),
        .Q(Q),
        .RCO(RCO)
    );

    // Initialize the inputs
    initial begin
        $dumpfile("sumador8_tb.vcd");
        $dumpvars(0, sumador8_tb);

        
        RCI = 0;

        // PRUEBA #1 SUMA DE 4 BITS
        MODO = 2'b11;
        ENB = 1;
        CLK = 0;

        #10;
        MODO = 2'b01;
        A = 8'd17;
        B = 8'd3;

        #10;
        A = 8'b11111111;
        B = 1'b1;

        #10;
        A = 7;
        B = 2;

        #10;
        // PRUEBA #2 RESTA DE 4 BITS
        MODO = 2'b11; 

        #10;
        MODO = 2'b10;
        A = 4;
        B = 3;

        #10;
        A = 4'b1111;
        B = 1'b1;

        #10;
        A = 3;
        B = 8;

        #10;
        // PRUEBA #3 MANTENER EL VALOR EN MODO 00 
        MODO = 2'b01; // OPERACION INICIAL
        A = 5;
        B = 3;
        
        #10;
        MODO = 2'b00; // MANTENER RESULTADO DE SUMA

        #10;
        // PRUEBA #4 MANTENER EL VALOR CUANDO ENB = 0
        MODO = 2'b10; // OPERACION INICIAL
        A = 3;
        B = 1;

        #10;
        ENB = 0;

        #10;
        $finish;
    end

    // Toggle the clock signal
    always #5 CLK = ~CLK;

    
    

endmodule

Tarea 1/sumador8_tb.vcd
$date
	Tue Mar 28 20:59:10 2023
$end
$version
	Icarus Verilog
$end
$timescale
	1ns
$end
$scope module sumador8_tb $end
$var wire 1 ! RCO $end
$var wire 8 " Q [7:0] $end
$var reg 8 # A [7:0] $end
$var reg 8 $ B [7:0] $end
$var reg 1 % CLK $end
$var reg 1 & ENB $end
$var reg 2 ' MODO [1:0] $end
$var reg 1 ( RCI $end
$scope module dut $end
$var wire 8 ) A [7:0] $end
$var wire 8 * B [7:0] $end
$var wire 1 % CLK $end
$var wire 1 & ENB $end
$var wire 2 + MODO [1:0] $end
$var wire 1 ( RCI $end
$var wire 1 ! RCO $end
$var wire 4 , Q2 [3:0] $end
$var wire 4 - Q1 [3:0] $end
$var wire 8 . Q [7:0] $end
$var wire 1 / C1 $end
$var reg 1 0 W1 $end
$var reg 4 1 W2 [3:0] $end
$var reg 4 2 W3 [3:0] $end
$scope module bloque1 $end
$var wire 4 3 A [3:0] $end
$var wire 4 4 B [3:0] $end
$var wire 1 % CLK $end
$var wire 1 & ENB $end
$var wire 2 5 MODO [1:0] $end
$var wire 1 ( RCI $end
$var wire 4 6 negB [3:0] $end
$var reg 4 7 Q [3:0] $end
$var reg 1 / RCO $end
$upscope $end
$scope module bloque2 $end
$var wire 4 8 A [3:0] $end
$var wire 4 9 B [3:0] $end
$var wire 1 % CLK $end
$var wire 1 & ENB $end
$var wire 2 : MODO [1:0] $end
$var wire 1 0 RCI $end
$var wire 4 ; negB [3:0] $end
$var reg 4 < Q [3:0] $end
$var reg 1 ! RCO $end
$upscope $end
$upscope $end
$upscope $end
$enddefinitions $end
$comment Show the parameter values. $end
$dumpall
$end
#0
$dumpvars
bx <
bx ;
b11 :
bx 9
bx 8
bx 7
bx 6
b11 5
bx 4
bx 3
bx 2
bx 1
x0
x/
bx .
bx -
bx ,
b11 +
bx *
bx )
0(
b11 '
1&
0%
bx $
bx #
bx "
x!
$end
#5
bx0000 "
bx0000 .
b0 -
b0 7
1%
#10
b1101 6
b0 ;
b11 4
b0 9
00
b100 1
b1 3
b1 8
0%
b11 $
b11 *
b10001 #
b10001 )
b1 '
b1 +
b1 5
b1 :
#15
0!
b1 ,
b1 <
0/
b10100 "
b10100 .
b100 -
b100 7
1%
#20
b1111 6
b1 4
10
b0 1
b1111 3
b1111 8
0%
b1 $
b1 *
b11111111 #
b11111111 )
#25
1/
b0 -
b0 7
1!
b0 "
b0 .
b0 ,
b0 <
1%
#30
b1110 6
b10 4
00
b1001 1
b111 3
b0 8
0%
b10 $
b10 *
b111 #
b111 )
#35
0!
0/
b1001 "
b1001 .
b1001 -
b1001 7
1%
#40
0%
b11 '
b11 +
b11 5
b11 :
#45
b0 "
b0 .
b0 -
b0 7
1%
#50
b1101 6
b11 4
b1 1
b1101 2
b100 3
0%
b11 $
b11 *
b100 #
b100 )
b10 '
b10 +
b10 5
b10 :
#55
b1 "
b1 .
b1 -
b1 7
1%
#60
b1111 6
b1 4
b1110 1
b1111 2
b1111 3
0%
b1 $
b1 *
b1111 #
b1111 )
#65
b1110 "
b1110 .
b1110 -
b1110 7
1%
#70
b1000 6
b1000 4
10
b1011 1
b1000 2
b11 3
0%
b1000 $
b1000 *
b11 #
b11 )
#75
1!
b1111 ,
b1111 <
1/
b11111011 "
b11111011 .
b1011 -
b1011 7
1%
#80
b1101 6
b11 4
00
b1000 1
b101 3
0%
b11 $
b11 *
b101 #
b101 )
b1 '
b1 +
b1 5
b1 :
#85
0/
b1000 -
b1000 7
0!
b1000 "
b1000 .
b0 ,
b0 <
1%
#90
0%
b0 '
b0 +
b0 5
b0 :
#95
1%
#100
b1111 6
b1 4
b10 1
b1111 2
b11 3
0%
b1 $
b1 *
b11 #
b11 )
b10 '
b10 +
b10 5
b10 :
#105
b10 "
b10 .
b10 -
b10 7
1%
#110
0%
0&
